{
	"info": {
		"_postman_id": "19f6760a-555c-4542-8caf-9cf01341b470",
		"name": "MS Catalogo de Produtos (local)",
		"schema": "https://schema.getpostman.com/json/collection/v2.1.0/collection.json"
	},
	"item": [
		{
			"name": "Categorias",
			"item": [
				{
					"name": "Categorias",
					"request": {
						"method": "GET",
						"header": [],
						"url": {
							"raw": "{{API_CatalogoProdutos}}/categorias",
							"host": [
								"{{API_CatalogoProdutos}}"
							],
							"path": [
								"categorias"
							]
						}
					},
					"response": []
				},
				{
					"name": "Carregar",
					"request": {
						"method": "GET",
						"header": [],
						"url": {
							"raw": "{{API_CatalogoProdutos}}/categorias/carregar/1/6058ce44a4dcd51460fa7f38",
							"host": [
								"{{API_CatalogoProdutos}}"
							],
							"path": [
								"categorias",
								"carregar",
								"1",
								"6058ce44a4dcd51460fa7f38"
							]
						}
					},
					"response": []
				},
				{
					"name": "Listar",
					"request": {
						"method": "GET",
						"header": [],
						"url": {
							"raw": "{{API_CatalogoProdutos}}/categorias/listar/1",
							"host": [
								"{{API_CatalogoProdutos}}"
							],
							"path": [
								"categorias",
								"listar",
								"1"
							]
						}
					},
					"response": []
				},
				{
					"name": "Criar",
					"request": {
						"method": "POST",
						"header": [
							{
								"key": "Content-Type",
								"value": "application/json",
								"type": "text"
							}
						],
						"body": {
							"mode": "raw",
							"raw": "{\r\n    \"idProprietario\": \"1\",\r\n    \"nome\": \"Bebidas\"\r\n}"
						},
						"url": {
							"raw": "{{API_CatalogoProdutos}}/categorias/adicionar",
							"host": [
								"{{API_CatalogoProdutos}}"
							],
							"path": [
								"categorias",
								"adicionar"
							]
						}
					},
					"response": []
				},
				{
					"name": "Deletar",
					"request": {
						"method": "DELETE",
						"header": [],
						"body": {
							"mode": "raw",
							"raw": ""
						},
						"url": {
							"raw": "{{API_CatalogoProdutos}}/categorias/deletar/1/6059e863a519021ae01aaf41",
							"host": [
								"{{API_CatalogoProdutos}}"
							],
							"path": [
								"categorias",
								"deletar",
								"1",
								"6059e863a519021ae01aaf41"
							]
						}
					},
					"response": []
				},
				{
					"name": "Alterar",
					"request": {
						"method": "PATCH",
						"header": [
							{
								"key": "Content-Type",
								"value": "application/json",
								"type": "text"
							}
						],
						"body": {
							"mode": "raw",
							"raw": "{\r\n    \"nome\": \"Pizza_alterado\"\r\n}"
						},
						"url": {
							"raw": "{{API_CatalogoProdutos}}/categorias/alterar/1/6059e863a519021ae01aaf41",
							"host": [
								"{{API_CatalogoProdutos}}"
							],
							"path": [
								"categorias",
								"alterar",
								"1",
								"6059e863a519021ae01aaf41"
							]
						}
					},
					"response": []
				}
			]
		},
		{
			"name": "Produtos",
			"item": [
				{
					"name": "Produtos",
					"request": {
						"method": "GET",
						"header": [],
						"url": {
							"raw": "{{API_CatalogoProdutos}}/produtos",
							"host": [
								"{{API_CatalogoProdutos}}"
							],
							"path": [
								"produtos"
							]
						}
					},
					"response": []
				},
				{
					"name": "Carregar",
					"request": {
						"method": "GET",
						"header": [],
						"url": {
							"raw": "{{API_CatalogoProdutos}}/produtos/carregar/1/6059dea21e45751bb436b715",
							"host": [
								"{{API_CatalogoProdutos}}"
							],
							"path": [
								"produtos",
								"carregar",
								"1",
								"6059dea21e45751bb436b715"
							]
						}
					},
					"response": []
				},
				{
					"name": "Listar",
					"request": {
						"method": "GET",
						"header": [],
						"url": {
							"raw": "{{API_CatalogoProdutos}}/produtos/listar/1",
							"host": [
								"{{API_CatalogoProdutos}}"
							],
							"path": [
								"produtos",
								"listar",
								"1"
							]
						}
					},
					"response": []
				},
				{
					"name": "Criar",
					"request": {
						"method": "POST",
						"header": [
							{
								"key": "Content-Type",
								"value": "application/json",
								"type": "text"
							}
						],
						"body": {
							"mode": "raw",
							"raw": "{\r\n    \"idProprietario\": \"1\",\r\n    \"nome\": \"XBacon\",\r\n    \"descricao\": \"lanche\",\r\n    \"valor1\": 15.0,\r\n    \"valor2\": 0,\r\n    \"valor3\": 0,\r\n    \"ativo\": true,\r\n    \"categorias\": [\r\n        {\r\n            \"_id\": \"6058ce5da4dcd51460fa7f39\"\r\n        }\r\n    ],\r\n    \"paineisModificacao\": [\r\n        {\r\n            \"nome\": \"Extras\",\r\n            \"min\": 0,\r\n            \"max\": 1,\r\n            \"modificacoes\": [\r\n                {\r\n                    \"nome\": \"Bacon\",\r\n                    \"valor\": 2.0\r\n                }\r\n            ]\r\n        }\r\n    ]\r\n}"
						},
						"url": {
							"raw": "{{API_CatalogoProdutos}}/produtos/adicionar",
							"host": [
								"{{API_CatalogoProdutos}}"
							],
							"path": [
								"produtos",
								"adicionar"
							]
						}
					},
					"response": []
				},
				{
					"name": "Deletar",
					"request": {
						"method": "DELETE",
						"header": [],
						"url": {
							"raw": "{{API_CatalogoProdutos}}/produtos/deletar/1/6059e9dba519021ae01aaf45",
							"host": [
								"{{API_CatalogoProdutos}}"
							],
							"path": [
								"produtos",
								"deletar",
								"1",
								"6059e9dba519021ae01aaf45"
							]
						}
					},
					"response": []
				},
				{
					"name": "Alterar",
					"request": {
						"method": "PATCH",
						"header": [
							{
								"key": "Content-Type",
								"value": "application/json",
								"type": "text"
							}
						],
						"body": {
							"mode": "raw",
							"raw": "{\r\n    \"nome\": \"XSalada\",\r\n    \"valor1\": 14.00,\r\n    \"valor2\": 14.00,\r\n    \"valor3\": 14.00,\r\n    \"ativo\": false\r\n}"
						},
						"url": {
							"raw": "{{API_CatalogoProdutos}}/produtos/alterar/1/6059e94aa519021ae01aaf42",
							"host": [
								"{{API_CatalogoProdutos}}"
							],
							"path": [
								"produtos",
								"alterar",
								"1",
								"6059e94aa519021ae01aaf42"
							]
						}
					},
					"response": []
				}
			]
		}
	],
	"variable": [
		{
			"key": "API_CatalogoProdutos",
			"value": "localhost:3333"
		}
	]
}